pypaytabs/Exceptions.py
pypaytabs/Paytabs.py
pypaytabs/Utilities.py
pypaytabs/__init__.py
pypaytabs-1.0.1.dist-info/METADATA
pypaytabs-1.0.1.dist-info/WHEEL
pypaytabs-1.0.1.dist-info/top_level.txt
pypaytabs-1.0.1.dist-info/RECORD
