Metadata-Version: 2.1
Name: pypaytabs
Version: 1.0.1
Summary: PyPaytabs is a Python library for Paytabs Payment Gateway.
Home-page: https://github.com/itiblog/pypaytabs
Author: Belal Salah, Mohamed Hammad
Author-email: belalsalah140@gmail.com, mmhy2003@gmail.com
License: MIT
Platform: UNKNOWN
Classifier: License :: OSI Approved :: MIT License
Classifier: Programming Language :: Python :: 3
Classifier: Programming Language :: Python :: 3.6
